qlan_services_common_lib/__init__.py
qlan_services_common_lib/libs/__init__.py
qlan_services_common_lib/libs/database/__init__.py
qlan_services_common_lib/libs/database/connection/__init__.py
qlan_services_common_lib/libs/database/connection/solr.py
qlan_services_common_lib/libs/services/__init__.py
qlan_services_common_lib/libs/services/cache/__init__.py
qlan_services_common_lib/libs/services/cache/base.py
qlan_services_common_lib/libs/services/cache/user_profile/__init__.py
qlan_services_common_lib/libs/services/cache/user_profile/user_accounts.py
qlan_services_common_lib/libs/services/cache/user_profile/user_profile_type.py
qlan_services_common_lib/libs/services/common/__init__.py
qlan_services_common_lib/libs/services/common/user_profile/__init__.py
qlan_services_common_lib/libs/services/common/user_profile/profile.py
qlan_services_common_lib/libs/services/solr/__init__.py
qlan_services_common_lib/libs/services/solr/userprofile.py
qlan_common_libs-0.1.20.dist-info/METADATA
qlan_common_libs-0.1.20.dist-info/WHEEL
qlan_common_libs-0.1.20.dist-info/top_level.txt
qlan_common_libs-0.1.20.dist-info/RECORD
