Metadata-Version: 2.1
Name: qlan-common-libs
Version: 0.1.20
Summary: A collection of common functions for various tasks.
Author: Qlan
Classifier: Programming Language :: Python :: 3
Classifier: License :: OSI Approved :: MIT License
Classifier: Operating System :: OS Independent
Requires-Python: >=3.11
